<?xml version="1.0"?>
<persistence xmlns="http://java.sun.com/xml/ns/persistence"
             xmlns:xsi="http://www.w3.org/2001/XMLSchema-instance"
             xsi:schemaLocation="http://java.sun.com/xml/ns/persistence http://www.oracle.com/webfolder/technetwork/jsc/xml/ns/persistence/persistence_2_0.xsd"
             version="2.0">

    <persistence-unit name="DefaultPersistenceUnit" transaction-type="RESOURCE_LOCAL">
    	<class>com.google.gwt.sample.dynatablemvp.server.domain.Address</class>
    	<class>com.google.gwt.sample.dynatablemvp.server.domain.Person</class>
    	<class>com.google.gwt.sample.dynatablemvp.server.domain.Schedule</class>
    	<class>com.google.gwt.sample.dynatablemvp.server.domain.TimeSlot</class>
    </persistence-unit>
</persistence>